CHANGES.rst
MANIFEST.in
README.rst
TODO.rst
setup.py
django_stockandflow.egg-info/PKG-INFO
django_stockandflow.egg-info/SOURCES.txt
django_stockandflow.egg-info/dependency_links.txt
django_stockandflow.egg-info/not-zip-safe
django_stockandflow.egg-info/top_level.txt
stockandflow/__init__.py
stockandflow/admin.py
stockandflow/geckoboard_urls.py
stockandflow/models.py
stockandflow/periodic.py
stockandflow/tests.py
stockandflow/tracker.py
stockandflow/views.py