Metadata-Version: 1.0
Name: django-stockandflow
Version: 0.0.4
Summary: Django stock and flow tracking for business intelligence metrics
Home-page: http://github.com/jesseh/django-stockandflow/
Author: Jesse Heitler
Author-email: jesseh@i-iterate.com
License: LICENSE.txt
Platform: UNKNOWN
Classifier: Development Status :: 3 - Alpha
Classifier: Environment :: Web Environment
Classifier: Intended Audience :: Developers
Classifier: Operating System :: OS Independent
Classifier: Programming Language :: Python
Classifier: Framework :: Django
